nafcodec/pyfile.rs
nafcodec/lib.pyi
nafcodec/lib.rs
nafcodec/__init__.py
nafcodec/build.rs
nafcodec/lib.cpython-311-darwin.so
nafcodec/py.typed
nafcodec/tests/test_decoder.py
nafcodec/tests/requirements.txt
nafcodec/tests/test_encoder.py
nafcodec/tests/__init__.py
nafcodec/tests/unittest.rs
nafcodec/tests/test_open.py
nafcodec/tests/test_doctest.py
nafcodec/tests/data/CP040672.naf
nafcodec/tests/data/masked.naf
nafcodec/tests/data/LuxC.naf
nafcodec/tests/data/__init__.py
nafcodec/tests/data/phix.naf
nafcodec-0.3.1.dist-info/RECORD
nafcodec-0.3.1.dist-info/WHEEL
nafcodec-0.3.1.dist-info/METADATA
nafcodec-0.3.1.dist-info/licenses/COPYING
