Metadata-Version: 2.4
Name: nafcodec
Version: 0.3.1
Classifier: Development Status :: 3 - Alpha
Classifier: Intended Audience :: Developers
Classifier: Intended Audience :: Science/Research
Classifier: License :: OSI Approved :: MIT License
Classifier: Operating System :: OS Independent
Classifier: Programming Language :: Rust
Classifier: Programming Language :: Python :: 3.7
Classifier: Programming Language :: Python :: 3.8
Classifier: Programming Language :: Python :: 3.9
Classifier: Programming Language :: Python :: 3.10
Classifier: Programming Language :: Python :: 3.11
Classifier: Programming Language :: Python :: 3.12
Classifier: Programming Language :: Python :: 3.13
Classifier: Programming Language :: Python :: Implementation :: CPython
Classifier: Programming Language :: Python :: Implementation :: PyPy
Classifier: Topic :: Scientific/Engineering :: Bio-Informatics
Classifier: Topic :: Scientific/Engineering :: Medical Science Apps.
Classifier: Topic :: Software Development :: Libraries :: Python Modules
Classifier: Typing :: Typed
License-File: COPYING
Summary: PyO3 bindings and Python interface to nafcodec, an encoder/decoder for Nucleotide Archive Format (NAF) files.
Keywords: nucleotide,archive,biology,bioinformatics
Home-Page: https://github.com/althonos/nafcodec
Author: Martin Larralde <martin.larralde@embl.de>
Author-email: Martin Larralde <martin.larralde@embl.de>
License: MIT
Requires-Python: >=3.7
Project-URL: Home Page, https://github.com/althonos/nafcodec/
Project-URL: Bug Tracker, https://github.com/althonos/nafcodec/issues
Project-URL: Changelog, https://github.com/althonos/nafcodec/blob/master/CHANGELOG.md
Project-URL: Coverage, https://codecov.io/gh/althonos/nafcodec/
Project-URL: Builds, https://github.com/althonos/nafcodec/actions/
Project-URL: PyPI, https://pypi.org/project/nafcodec
